googleflay/__init__.py
googleflay/exchange_rate.py
googleflay-0.0.1.dist-info/LICENSE
googleflay-0.0.1.dist-info/METADATA
googleflay-0.0.1.dist-info/WHEEL
googleflay-0.0.1.dist-info/top_level.txt
googleflay-0.0.1.dist-info/RECORD
